{"nodes": [{"id": "license", "label": "MIT License (License.txt)", "file_type": "document", "source_file": "License.txt", "source_location": null, "source_url": null, "captured_at": null, "author": null, "contributor": null}, {"id": "license_hbisoft", "label": "HBiSoft (copyright holder)", "file_type": "concept", "source_file": "License.txt", "source_location": null, "source_url": null, "captured_at": null, "author": null, "contributor": null}], "edges": [{"source": "license", "target": "readme", "relation": "conceptually_related_to", "confidence": "INFERRED", "confidence_score": 0.85, "source_file": "License.txt", "source_location": null, "weight": 1.0}, {"source": "license", "target": "license_hbisoft", "relation": "references", "confidence": "EXTRACTED", "confidence_score": 1.0, "source_file": "License.txt", "source_location": null, "weight": 1.0}], "hyperedges": []}