{"nodes": [{"id": "app_src_main_res_mipmap_mdpi_ic_launcher_round", "label": "ic_launcher_round.png (mdpi)", "file_type": "image", "source_file": "app/src/main/res/mipmap-mdpi/ic_launcher_round.png", "source_location": null, "source_url": null, "captured_at": null, "author": null, "contributor": null}, {"id": "concept_app_launcher_icon", "label": "App launcher icon (round variant)", "file_type": "concept", "source_file": "app/src/main/res/mipmap-mdpi/ic_launcher_round.png", "source_location": null, "source_url": null, "captured_at": null, "author": null, "contributor": null}, {"id": "concept_misty_screen_recorder_lite_app", "label": "Misty Screen Recorder (lite) Android app", "file_type": "concept", "source_file": "app/src/main/res/mipmap-mdpi/ic_launcher_round.png", "source_location": null, "source_url": null, "captured_at": null, "author": null, "contributor": null}], "edges": [{"source": "app_src_main_res_mipmap_mdpi_ic_launcher_round", "target": "concept_app_launcher_icon", "relation": "depicts", "confidence": "INFERRED", "confidence_score": 0.95, "source_file": "app/src/main/res/mipmap-mdpi/ic_launcher_round.png", "source_location": null, "weight": 1.0}, {"source": "concept_app_launcher_icon", "target": "concept_misty_screen_recorder_lite_app", "relation": "represents_brand_of", "confidence": "INFERRED", "confidence_score": 0.85, "source_file": "app/src/main/res/mipmap-mdpi/ic_launcher_round.png", "source_location": null, "weight": 1.0}, {"source": "app_src_main_androidmanifest_xml", "target": "app_src_main_res_mipmap_mdpi_ic_launcher_round", "relation": "references_as_roundIcon", "confidence": "AMBIGUOUS", "confidence_score": 0.3, "source_file": "app/src/main/res/mipmap-mdpi/ic_launcher_round.png", "source_location": null, "weight": 0.6}], "hyperedges": []}